deltasnap/__init__.py
deltasnap-0.1.2.dist-info/LICENSE.md
deltasnap-0.1.2.dist-info/METADATA
deltasnap-0.1.2.dist-info/WHEEL
deltasnap-0.1.2.dist-info/top_level.txt
deltasnap-0.1.2.dist-info/RECORD
