Metadata-Version: 2.1
Name: deltasnap
Version: 0.1.2
Summary: Library for processing and managing database metadata
Home-page: UNKNOWN
Author: Matias Viola
Author-email: matiasvioladi@gmail.com
License: MIT
Keywords: metadata management,database,SQLAlchemy,Django,functional testing,debugging,ORM,database capture,data analysis,data comparison,database records,test automation,test framework,database testing,software testing
Platform: UNKNOWN
Classifier: Programming Language :: Python :: 3.6
Classifier: License :: OSI Approved :: MIT License
Classifier: Operating System :: OS Independent
Classifier: Topic :: Software Development :: Libraries
Classifier: Intended Audience :: Developers
Requires-Python: >=3.6
License-File: LICENSE.md
Provides-Extra: all
Requires-Dist: Django>=3.0; extra == "all"
Requires-Dist: SQLAlchemy>=1.3; extra == "all"
Provides-Extra: django
Requires-Dist: Django>=3.0; extra == "django"
Provides-Extra: sqlalchemy
Requires-Dist: SQLAlchemy>=1.3; extra == "sqlalchemy"
